promptic.py
promptic-5.5.1.dist-info/licenses/LICENSE
promptic-5.5.1.dist-info/WHEEL
promptic-5.5.1.dist-info/METADATA
promptic-5.5.1.dist-info/RECORD
