Metadata-Version: 2.4
Name: promptic
Version: 5.5.1
Summary: 90% of what you need for LLM app development. Nothing you don't.
Author-email: Stephan Fitzpatrick <stephan@knowsuchagency.com>
Requires-Python: >=3.11
Classifier: License :: OSI Approved :: Apache Software License
Classifier: Programming Language :: Python :: 3
Classifier: Programming Language :: Python :: 3.11
Classifier: Programming Language :: Python :: 3.12
Classifier: Programming Language :: Python :: 3.13
License-File: LICENSE
Requires-Dist: jsonschema>=4.23.0
Requires-Dist: litellm~=1.38
Requires-Dist: pydantic~=2.7
Project-URL: Home, https://github.com/knowsuchagency/promptic
